{
    "26": {
        "a": {
            "kommentare": [
                {
                    "zifferNr": "26",
                    "title": "Nr. 26 und zusätzliche Leistungen",
                    "text": "<p>Grundsätzlich gilt, dass der Leistungsinhalt der Nr. 26 (Früherkennung von Krankheiten bei einem Kind) neben der Anamnese auch die Feststellung der Körpermaße, die Untersuchung des Nervensystems, der Sinnesorgane, des Skelettsystems, der Haut, der Brust, des Bauchs und der Geschlechtsorgane beinhaltet. Ebenfalls eingeschlossen ist eine Beratung der Bezugsperson.</p><p>Die vorgenannten Untersuchungsziele beinhalten letztlich eine komplette Untersuchung des Kindes. Nur wenn hierbei entsprechende Auffälligkeiten festgestellt werden, die über den Leistungsinhalt einer Ganzkörperuntersuchung hinausgehende Untersuchungen erforderlich machen, können diese Untersuchungen auch abgerechnet werden.</p><p>Das häufig gebrachte Argument, dass es sinnvoll ist, eine Erkrankung auszuschließen, führe letztlich dazu, dass sämtliche Untersuchungsverfahren durchgeführt und auch abgerechnet werden könnten. Nur um das Problem an einem Beispiel darzustellen, könnte mit dieser Argumentation auch zusätzlich ein EEG durchgeführt werden, nur um ein Krampfleiden auszuschließen. Diese Vorgehensweise bei der Durchführung und Abrechnung von Früherkennungsuntersuchungen ist nicht zulässig. Nur Verdachtsdiagnosen als Ergebnis der Früherkennungsuntersuchung rechtfertigen weitere Untersuchungsmaßnahmen.</p><p></p><p></p>",
                    "categories": [
                        "Früherkennungsuntersuchung",
                        "zusätzliche Leistungen"
                    ]
                }
            ]
        }
    }
}